nonstdout/__init__.py
nonstdout/core.py
nonstdout-1.0.4.dist-info/LICENSE
nonstdout-1.0.4.dist-info/METADATA
nonstdout-1.0.4.dist-info/WHEEL
nonstdout-1.0.4.dist-info/top_level.txt
nonstdout-1.0.4.dist-info/RECORD
