Metadata-Version: 2.1
Name: nonstdout
Version: 1.0.4
Summary: A Python library for making printing cooler with colours and loading bars.
Home-page: https://github.com/Sushii64/nonstdout
Author: Sushii64
License: GNU GPL V3
Classifier: Development Status :: 4 - Beta
Classifier: Intended Audience :: Developers
Classifier: Programming Language :: Python :: 3
Classifier: Topic :: Software Development :: Libraries
Classifier: Topic :: Utilities
License-File: LICENSE
Requires-Dist: colorama ==0.4.6
